<workunit>
    <invokers>
        <invoker folderid="/txn/treasury" action="create" caption="Request Accountable Form" target="window"/>
    </invokers>
    
    <code>
        <![CDATA[
        
            import com.rameses.rcp.annotations.*
            import com.rameses.rcp.common.*
            import com.rameses.osiris2.client.*
            import com.rameses.osiris2.common.*

            class RISController {
                
                String title = "Requisition Issue Slip";
                def risTypes;  
                def risType;
            
                void create() {
                    risTypes = InvokerUtil.lookupOpeners( "ris:types", [:] );
                }
            }
            
     ]]>
    </code>
    
    <pages>
        <page template="com.rameses.gov.treasury.ris.RISInitialPage"/>
    </pages>
</workunit>