<workunit extends="wtemplates/enterprise/treasury/BasicCashReceiptController.xml">
    <invokers>
        <invoker type="cashreceipt:cashticket" action="init" />
    </invokers>
    
    <code>
        <![CDATA[    
        import com.rameses.rcp.annotations.*
        import com.rameses.rcp.common.*
        import com.rameses.osiris2.client.*
        import com.rameses.osiris2.common.*
        import com.rameses.enterprise.treasury.controllers.*
        
        class  CashTicketReceiptController extends BasicCashReceipt {
            
            String title = "Cash Ticket " ;
        
        }
        ]]>
        
    </code>
    
    <pages>
        <page template="com.rameses.gov.treasury.cashticket.CashTicketReceiptPage"/>
    </pages>
    
</workunit>